cursely/__init__.py
cursely/__main__.py
cursely/cursely_push_config
cursely/modpacks/latest_alpha.mods
cursely/modpacks/latest_alpha_config.zip
cursely/modpacks/magical_souls.mods
cursely/modpacks/magical_souls.resolved-mods
cursely/modpacks/magical_souls_config.zip
cursely/modpacks/magical_souls_lite.mods
cursely/modpacks/magical_souls_lite_config.zip
cursely/modpacks/zombies.mods
cursely/modpacks/zombies_config.zip
cursely/modules/__init__.py
cursely/modules/config.py
cursely/modules/dependencies.py
cursely/modules/downloads.py
cursely/modules/files.py
cursely/modules/lockfile.py
cursely/modules/modpack.py
cursely/modules/modpack_config.py
cursely/modules/modpack_statements.py
cursely/modules/mods.py
cursely/modules/search.py
cursely-0.8.0.dist-info/METADATA
cursely-0.8.0.dist-info/WHEEL
cursely-0.8.0.dist-info/entry_points.txt
cursely-0.8.0.dist-info/RECORD
