Metadata-Version: 2.1
Name: cursely
Version: 0.8.0
Summary: Cross-platform mod management for Minecraft.
Home-page: https://github.com/Julynx/cursely
Author: Julynx
Requires-Python: >=3.10,<4.0
Classifier: Programming Language :: Python :: 3
Classifier: Programming Language :: Python :: 3.10
Classifier: Programming Language :: Python :: 3.11
Classifier: Programming Language :: Python :: 3.12
Requires-Dist: numerize (>=0.12,<0.13)
Requires-Dist: ordered-set-37 (>=2.0,<3.0)
Requires-Dist: prettytable (>=3.10.0,<4.0.0)
Requires-Dist: requests (>=2.32.3,<3.0.0)
